im_critsec/__init__.py
im_critsec-0.0.4.dist-info/DESCRIPTION.rst
im_critsec-0.0.4.dist-info/METADATA
im_critsec-0.0.4.dist-info/RECORD
im_critsec-0.0.4.dist-info/WHEEL
im_critsec-0.0.4.dist-info/metadata.json
im_critsec-0.0.4.dist-info/top_level.txt
